{
  "accentColor": "{{appsmith.theme.colors.primaryColor}}",
  "animateLoading": true,
  "autoFocus": false,
  "borderRadius": "{{appsmith.theme.borderRadius.appBorderRadius}}",
  "bottomRow": 34,
  "boxShadow": "none",
  "defaultText": "",
  "dynamicBindingPathList": [
    {
      "key": "accentColor"
    },
    {
      "key": "borderRadius"
    }
  ],
  "dynamicHeight": "FIXED",
  "dynamicTriggerPathList": [],
  "iconAlign": "left",
  "iconName": "lock",
  "inputType": "TEXT",
  "isDisabled": false,
  "isLoading": false,
  "isRequired": false,
  "isVisible": true,
  "key": "c3i7xtebj0",
  "label": "",
  "labelAlignment": "left",
  "labelPosition": "Top",
  "labelStyle": "",
  "labelTextSize": "0.875rem",
  "labelWidth": 5,
  "leftColumn": 5,
  "maxDynamicHeight": 9000,
  "minDynamicHeight": 4,
  "minWidth": 450,
  "mobileBottomRow": 20,
  "mobileLeftColumn": 17,
  "mobileRightColumn": 37,
  "mobileTopRow": 13,
  "needsErrorInfo": false,
  "parentColumnSpace": 4.5859375,
  "parentId": "o08uy9arzl",
  "parentRowSpace": 10,
  "placeholderText": "Senha",
  "renderMode": "CANVAS",
  "resetOnSubmit": true,
  "responsiveBehavior": "fill",
  "rightColumn": 54,
  "showStepArrows": false,
  "topRow": 30,
  "type": "INPUT_WIDGET_V2",
  "version": 2,
  "widgetId": "rcy9esv892",
  "widgetName": "Input2Copy1"
}